smprofiler/__init__.py
smprofiler/py.typed
smprofiler/util.py
smprofiler/apiserver/__init__.py
smprofiler/apiserver/app/__init__.py
smprofiler/apiserver/app/headers.py
smprofiler/apiserver/app/main.py
smprofiler/apiserver/app/validation.py
smprofiler/apiserver/app/versions.py
smprofiler/apiserver/request_scheduling/__init__.py
smprofiler/apiserver/request_scheduling/computation_scheduler.py
smprofiler/apiserver/request_scheduling/counts_scheduler.py
smprofiler/apiserver/request_scheduling/metrics_job_queue_insertion.py
smprofiler/apiserver/request_scheduling/ondemand_requester.py
smprofiler/apiserver/request_scheduling/proximity_scheduler.py
smprofiler/apiserver/request_scheduling/squidpy_scheduler.py
smprofiler/apiserver/scripts/__init__.py
smprofiler/apiserver/scripts/dump_schema.py
smprofiler/db/__init__.py
smprofiler/db/check_tables.py
smprofiler/db/cohorts.py
smprofiler/db/create_data_analysis_study.py
smprofiler/db/credentials.py
smprofiler/db/database_connection.py
smprofiler/db/describe_features.py
smprofiler/db/feature_matrix_extractor.py
smprofiler/db/importance_score_transcriber.py
smprofiler/db/modify_constraints.py
smprofiler/db/ondemand_dropper.py
smprofiler/db/ondemand_studies_index.py
smprofiler/db/publish_promote.py
smprofiler/db/querying.py
smprofiler/db/representative_subsample.py
smprofiler/db/schema_infuser.py
smprofiler/db/shapefile_polygon.py
smprofiler/db/simple_method_cache.py
smprofiler/db/simple_query_patterns.py
smprofiler/db/source_file_parser_interface.py
smprofiler/db/sqlite_builder.py
smprofiler/db/squidpy_metrics.py
smprofiler/db/stratification_puller.py
smprofiler/db/study_dropper.py
smprofiler/db/study_tokens.py
smprofiler/db/verbose_sql_execution.py
smprofiler/db/accessors/__init__.py
smprofiler/db/accessors/cells.py
smprofiler/db/accessors/feature_names.py
smprofiler/db/accessors/graphs.py
smprofiler/db/accessors/phenotypes.py
smprofiler/db/accessors/study.py
smprofiler/db/data_model/__init__.py
smprofiler-1.0.67.dist-info/METADATA
smprofiler-1.0.67.dist-info/WHEEL
smprofiler-1.0.67.dist-info/entry_points.txt
smprofiler-1.0.67.dist-info/top_level.txt
smprofiler-1.0.67.dist-info/RECORD
