Metadata-Version: 2.4
Name: smprofiler
Version: 1.0.67
Summary: Toolbox for spatial analysis of single cell data.
Author-email: James Mathews <mathewj2@mskcc.org>
Project-URL: documentation, https://github.com/nadeemlab/SMProfiler
Project-URL: repository, https://github.com/nadeemlab/SMProfiler
Classifier: Programming Language :: Python :: 3
Classifier: Topic :: Scientific/Engineering
Classifier: Intended Audience :: Science/Research
Requires-Python: >=3.13
Requires-Dist: attrs
Requires-Dist: boto3
Requires-Dist: botocore
Requires-Dist: cattrs
Requires-Dist: jinja2
Requires-Dist: numba>=0.44.0
Requires-Dist: psycopg
Requires-Dist: pyshp
Requires-Dist: pytz
Requires-Dist: requests
Requires-Dist: termplotlib
Provides-Extra: all
Requires-Dist: adiscstudies; extra == "all"
Requires-Dist: attrs; extra == "all"
Requires-Dist: bokeh; extra == "all"
Requires-Dist: boto3; extra == "all"
Requires-Dist: botocore; extra == "all"
Requires-Dist: Brotli; extra == "all"
Requires-Dist: cattrs; extra == "all"
Requires-Dist: cryptography; extra == "all"
Requires-Dist: dask[dataframe]; extra == "all"
Requires-Dist: dask-expr; extra == "all"
Requires-Dist: fastapi; extra == "all"
Requires-Dist: h5py; extra == "all"
Requires-Dist: jinja2; extra == "all"
Requires-Dist: matplotlib; extra == "all"
Requires-Dist: networkx; extra == "all"
Requires-Dist: numcodecs==0.15.1; extra == "all"
Requires-Dist: numpy; extra == "all"
Requires-Dist: pandas; extra == "all"
Requires-Dist: psycopg; extra == "all"
Requires-Dist: pydantic; extra == "all"
Requires-Dist: PyJWT; extra == "all"
Requires-Dist: pyshp; extra == "all"
Requires-Dist: pytz; extra == "all"
Requires-Dist: requests; extra == "all"
Requires-Dist: secure; extra == "all"
Requires-Dist: scipy; extra == "all"
Requires-Dist: scikit-learn; extra == "all"
Requires-Dist: squidpy>=1.6.2; extra == "all"
Requires-Dist: zarr<3; extra == "all"
Requires-Dist: tables; extra == "all"
Requires-Dist: tabulate; extra == "all"
Requires-Dist: termplotlib; extra == "all"
Requires-Dist: tqdm; extra == "all"
Requires-Dist: umap-learn; extra == "all"
Requires-Dist: uvicorn; extra == "all"
Requires-Dist: zstandard; extra == "all"
Provides-Extra: apiserver
Requires-Dist: adiscstudies; extra == "apiserver"
Requires-Dist: attrs; extra == "apiserver"
Requires-Dist: Brotli; extra == "apiserver"
Requires-Dist: cryptography; extra == "apiserver"
Requires-Dist: fastapi; extra == "apiserver"
Requires-Dist: matplotlib; extra == "apiserver"
Requires-Dist: networkx; extra == "apiserver"
Requires-Dist: pandas; extra == "apiserver"
Requires-Dist: psycopg; extra == "apiserver"
Requires-Dist: pydantic; extra == "apiserver"
Requires-Dist: PyJWT; extra == "apiserver"
Requires-Dist: pytz; extra == "apiserver"
Requires-Dist: requests; extra == "apiserver"
Requires-Dist: scipy; extra == "apiserver"
Requires-Dist: secure; extra == "apiserver"
Requires-Dist: uvicorn; extra == "apiserver"
Requires-Dist: zstandard; extra == "apiserver"
Provides-Extra: graphs
Requires-Dist: bokeh; extra == "graphs"
Requires-Dist: h5py; extra == "graphs"
Requires-Dist: matplotlib; extra == "graphs"
Requires-Dist: networkx; extra == "graphs"
Requires-Dist: requests; extra == "graphs"
Requires-Dist: tables; extra == "graphs"
Provides-Extra: ondemand
Requires-Dist: attrs; extra == "ondemand"
Requires-Dist: cattrs; extra == "ondemand"
Requires-Dist: Brotli; extra == "ondemand"
Requires-Dist: dask[dataframe]; extra == "ondemand"
Requires-Dist: dask-expr; extra == "ondemand"
Requires-Dist: numpy; extra == "ondemand"
Requires-Dist: numcodecs==0.15.1; extra == "ondemand"
Requires-Dist: pandas; extra == "ondemand"
Requires-Dist: psycopg; extra == "ondemand"
Requires-Dist: pydantic; extra == "ondemand"
Requires-Dist: scipy; extra == "ondemand"
Requires-Dist: scikit-learn; extra == "ondemand"
Requires-Dist: squidpy>=1.6.2; extra == "ondemand"
Requires-Dist: zarr<3; extra == "ondemand"
Requires-Dist: tabulate; extra == "ondemand"
Requires-Dist: tqdm; extra == "ondemand"
Requires-Dist: umap-learn; extra == "ondemand"
Requires-Dist: zstandard; extra == "ondemand"
Provides-Extra: dev
Requires-Dist: autopep8; extra == "dev"
Requires-Dist: mypy; extra == "dev"
Requires-Dist: pylint; extra == "dev"
Requires-Dist: pytest; extra == "dev"
